README.rst
setup.py
ommr/__init__.py
ommr/commands.py
ommr/processing.py
ommr.egg-info/PKG-INFO
ommr.egg-info/SOURCES.txt
ommr.egg-info/dependency_links.txt
ommr.egg-info/entry_points.txt
ommr.egg-info/requires.txt
ommr.egg-info/top_level.txt