Metadata-Version: 2.1
Name: ommr
Version: 0.1.0
Summary: A simple Micromouse Maze Simulator server
Home-page: https://github.com/Theseus/ommr
Author: Miguel Sánchez de León Peque
Author-email: peque@neosit.es
License: BSD License
Keywords: micromouse optical maze server recognition
Platform: UNKNOWN
Classifier: Development Status :: 3 - Alpha
Classifier: Topic :: Utilities
Classifier: License :: OSI Approved :: BSD License
Classifier: Programming Language :: Python :: 3
Classifier: Programming Language :: Python :: 3.6
Classifier: Programming Language :: Python :: Implementation :: CPython
Provides-Extra: test
